{
	"title":"A Perfect Fit",
	"status":"Released",
	"runtime":112,
	"revenue":0,
	"release_date":"2021-07-15",
	"production_countries":[
		"Indonesia"
	],
	"production_companies":[
		"Starvision Plus"
	],
	"poster_path":"\/nLwtsKUBhPcZKtrFQfVMpTxa7Of.jpg",
	"imdb_id":"tt13606090",
	"original_title":"A Perfect Fit",
	"overview":"Sparks fly when a fashion blogger in Bali meets a gifted shoemaker, leading her to question her commitment to her fiancé.",
	"original_language":"id",
	"adult":false,
	"budget":0,
	"genres":[
		"Comedy",
		"Drama",
		"Romance"
	],
	"slug":"a-perfect-fit",
	"gatsby_image_path":"..\/..\/images\/a-perfect-fit.jpg",
	"cast":[
		"Nadya Arina",
		"Refal Hady",
		"Giorgino Abraham",
		"Anggika Bölsterli",
		"Laura Theux",
		"Ayu Laksmi",
		"Unique Priscilla",
		"Karina Suwandi",
		"Dominique Sanda",
		"Bryan Domani"
	],
	"crew":[
		"Garin Nugroho",
		"Chand Parwez Servia",
		"Fiaz Servia",
		"Raza Servia",
		"Reza Servia",
		"Hadrah Daeng Ratu",
		"Aldie Harra",
		"Widhi Susila Utama",
		"Wawan I. Wibowo",
		"Herdanius Larobu"
	]
}