{
	"title":"A Silent Voice: The Movie",
	"status":"Released",
	"runtime":130,
	"revenue":30156463,
	"release_date":"2016-09-17",
	"production_countries":[
		"Japan"
	],
	"production_companies":[
		"Kyoto Animation",
		"ABC Animation",
		"Kodansha",
		"Pony Canyon",
		"Quaras",
		"Shochiku Co., Ltd."
	],
	"poster_path":"\/tuFaWiqX0TXoWu7DGNcmX3UW7sT.jpg",
	"imdb_id":"tt5323662",
	"original_title":"映画 聲の形",
	"overview":"Shouya Ishida starts bullying the new girl in class, Shouko Nishimiya, because she is deaf. But as the teasing continues, the rest of the class starts to turn on Shouya for his lack of compassion. When they leave elementary school, Shouko and Shouya do not speak to each other again... until an older, wiser Shouya, tormented by his past behaviour, decides he must see Shouko once more. He wants to atone for his sins, but is it already too late...?",
	"original_language":"ja",
	"adult":false,
	"budget":0,
	"genres":[
		"Animation",
		"Drama"
	],
	"slug":"a-silent-voice-the-movie",
	"gatsby_image_path":"..\/..\/images\/a-silent-voice-the-movie.jpg",
	"cast":[
		"Miyu Irino",
		"Saori Hayami",
		"Aoi Yuki",
		"Kensho Ono",
		"Yuki Kaneko",
		"Yui Ishikawa",
		"Megumi Han",
		"Toshiyuki Toyonaga",
		"Mayu Matsuoka",
		"Sachiko Kojima"
	],
	"crew":[
		"Roger Daltrey",
		"Pete Townshend",
		"Reiko Yoshida",
		"Yōta Tsuruoka",
		"John Entwistle",
		"Keith Moon",
		"Hideaki Hatta",
		"Eharu Oohashi",
		"Ryuuta Nakagami",
		"Kengo Shigemura"
	],
	"related_by_cast":[
		{
			"title":"The Garden of Words",
			"gatsby_image_path":"..\/..\/images\/the-garden-of-words.jpg",
			"slug":"the-garden-of-words"
		},
		{
			"title":"Saga of Tanya the Evil: The Movie",
			"gatsby_image_path":"..\/..\/images\/saga-of-tanya-the-evil-the-movie.jpg",
			"slug":"saga-of-tanya-the-evil-the-movie"
		},
		{
			"title":"Your Name.",
			"gatsby_image_path":"..\/..\/images\/your-name.jpg",
			"slug":"your-name"
		},
		{
			"title":"The Seven Deadly Sins the Movie: Cursed by Light",
			"gatsby_image_path":"..\/..\/images\/the-seven-deadly-sins-the-movie-cursed-by-light.jpg",
			"slug":"the-seven-deadly-sins-the-movie-cursed-by-light"
		},
		{
			"title":"The Seven Deadly Sins: Cursed by Light",
			"gatsby_image_path":"..\/..\/images\/the-seven-deadly-sins-cursed-by-light.jpg",
			"slug":"the-seven-deadly-sins-cursed-by-light"
		},
		{
			"title":"The Irregular at Magic High School: The Girl Who Summons the Stars",
			"gatsby_image_path":"..\/..\/images\/the-irregular-at-magic-high-school-the-girl-who-summons-the-stars.jpg",
			"slug":"the-irregular-at-magic-high-school-the-girl-who-summons-the-stars"
		},
		{
			"title":"The Day Naruto Became Hokage",
			"gatsby_image_path":"..\/..\/images\/the-day-naruto-became-hokage.jpg",
			"slug":"the-day-naruto-became-hokage"
		},
		{
			"title":"Spirited Away",
			"gatsby_image_path":"..\/..\/images\/spirited-away.jpg",
			"slug":"spirited-away"
		},
		{
			"title":"Saint Seiya: Legend of Sanctuary",
			"gatsby_image_path":"..\/..\/images\/saint-seiya-legend-of-sanctuary.jpg",
			"slug":"saint-seiya-legend-of-sanctuary"
		},
		{
			"title":"Naruto the Movie: Legend of the Stone of Gelel",
			"gatsby_image_path":"..\/..\/images\/naruto-the-movie-legend-of-the-stone-of-gelel.jpg",
			"slug":"naruto-the-movie-legend-of-the-stone-of-gelel"
		},
		{
			"title":"Naruto Shippuden the Movie: The Lost Tower",
			"gatsby_image_path":"..\/..\/images\/naruto-shippuden-the-movie-the-lost-tower.jpg",
			"slug":"naruto-shippuden-the-movie-the-lost-tower"
		},
		{
			"title":"Mobile Suit Gundam Hathaway",
			"gatsby_image_path":"..\/..\/images\/mobile-suit-gundam-hathaway.jpg",
			"slug":"mobile-suit-gundam-hathaway"
		},
		{
			"title":"Maquia: When the Promised Flower Blooms",
			"gatsby_image_path":"..\/..\/images\/maquia-when-the-promised-flower-blooms.jpg",
			"slug":"maquia-when-the-promised-flower-blooms"
		},
		{
			"title":"Kuroko no Basket Movie 3: Winter Cup Soushuuhen - Tobira no Mukou",
			"gatsby_image_path":"..\/..\/images\/kuroko-no-basket-movie-3-winter-cup-soushuuhen-tobira-no-mukou.jpg",
			"slug":"kuroko-no-basket-movie-3-winter-cup-soushuuhen-tobira-no-mukou"
		},
		{
			"title":"Kuroko no Basket Movie 1: Winter Cup Soushuuhen - Kage to Hikari",
			"gatsby_image_path":"..\/..\/images\/kuroko-no-basket-movie-1-winter-cup-soushuuhen-kage-to-hikari.jpg",
			"slug":"kuroko-no-basket-movie-1-winter-cup-soushuuhen-kage-to-hikari"
		},
		{
			"title":"Kizumonogatari Part 2: Nekketsu",
			"gatsby_image_path":"..\/..\/images\/kizumonogatari-part-2-nekketsu.jpg",
			"slug":"kizumonogatari-part-2-nekketsu"
		},
		{
			"title":"Is It Wrong to Try to Pick Up Girls in a Dungeon?: Arrow of the Orion",
			"gatsby_image_path":"..\/..\/images\/is-it-wrong-to-try-to-pick-up-girls-in-a-dungeon-arrow-of-the-orion.jpg",
			"slug":"is-it-wrong-to-try-to-pick-up-girls-in-a-dungeon-arrow-of-the-orion"
		},
		{
			"title":"In This Corner of the World",
			"gatsby_image_path":"..\/..\/images\/in-this-corner-of-the-world.jpg",
			"slug":"in-this-corner-of-the-world"
		},
		{
			"title":"Hunter x Hunter: The Last Mission",
			"gatsby_image_path":"..\/..\/images\/hunter-x-hunter-the-last-mission.jpg",
			"slug":"hunter-x-hunter-the-last-mission"
		},
		{
			"title":"Heaven's Lost Property Final – The Movie: Eternally My Master",
			"gatsby_image_path":"..\/..\/images\/heaven-s-lost-property-final-the-movie-eternally-my-master.jpg",
			"slug":"heaven-s-lost-property-final-the-movie-eternally-my-master"
		}
	],
	"related_most_similar":[
		{
			"title":"Beyond the Boundary: I'll Be Here - Past",
			"gatsby_image_path":"..\/..\/images\/beyond-the-boundary-i-ll-be-here-past.jpg",
			"slug":"beyond-the-boundary-i-ll-be-here-past"
		},
		{
			"title":"Love, Chunibyo & Other Delusions! Take On Me",
			"gatsby_image_path":"..\/..\/images\/love-chunibyo-other-delusions-take-on-me.jpg",
			"slug":"love-chunibyo-other-delusions-take-on-me"
		},
		{
			"title":"Love, Chunibyo & Other Delusions! Rikka Version",
			"gatsby_image_path":"..\/..\/images\/love-chunibyo-other-delusions-rikka-version.jpg",
			"slug":"love-chunibyo-other-delusions-rikka-version"
		},
		{
			"title":"The Garden of Words",
			"gatsby_image_path":"..\/..\/images\/the-garden-of-words.jpg",
			"slug":"the-garden-of-words"
		},
		{
			"title":"Fireworks",
			"gatsby_image_path":"..\/..\/images\/fireworks.jpg",
			"slug":"fireworks"
		},
		{
			"title":"Your Name.",
			"gatsby_image_path":"..\/..\/images\/your-name.jpg",
			"slug":"your-name"
		},
		{
			"title":"Saga of Tanya the Evil: The Movie",
			"gatsby_image_path":"..\/..\/images\/saga-of-tanya-the-evil-the-movie.jpg",
			"slug":"saga-of-tanya-the-evil-the-movie"
		},
		{
			"title":"Ride Your Wave",
			"gatsby_image_path":"..\/..\/images\/ride-your-wave.jpg",
			"slug":"ride-your-wave"
		},
		{
			"title":"Pretty Guardian Sailor Moon Eternal The Movie Part 2",
			"gatsby_image_path":"..\/..\/images\/pretty-guardian-sailor-moon-eternal-the-movie-part-2.jpg",
			"slug":"pretty-guardian-sailor-moon-eternal-the-movie-part-2"
		},
		{
			"title":"Mobile Suit Gundam Hathaway",
			"gatsby_image_path":"..\/..\/images\/mobile-suit-gundam-hathaway.jpg",
			"slug":"mobile-suit-gundam-hathaway"
		},
		{
			"title":"Maquia: When the Promised Flower Blooms",
			"gatsby_image_path":"..\/..\/images\/maquia-when-the-promised-flower-blooms.jpg",
			"slug":"maquia-when-the-promised-flower-blooms"
		},
		{
			"title":"Kizumonogatari Part 2: Nekketsu",
			"gatsby_image_path":"..\/..\/images\/kizumonogatari-part-2-nekketsu.jpg",
			"slug":"kizumonogatari-part-2-nekketsu"
		},
		{
			"title":"I Want to Eat Your Pancreas",
			"gatsby_image_path":"..\/..\/images\/i-want-to-eat-your-pancreas.jpg",
			"slug":"i-want-to-eat-your-pancreas"
		},
		{
			"title":"In This Corner of the World",
			"gatsby_image_path":"..\/..\/images\/in-this-corner-of-the-world.jpg",
			"slug":"in-this-corner-of-the-world"
		},
		{
			"title":"A Whisker Away",
			"gatsby_image_path":"..\/..\/images\/a-whisker-away.jpg",
			"slug":"a-whisker-away"
		},
		{
			"title":"Yes, No, or Maybe Half?",
			"gatsby_image_path":"..\/..\/images\/yes-no-or-maybe-half.jpg",
			"slug":"yes-no-or-maybe-half"
		},
		{
			"title":"Wolf Children",
			"gatsby_image_path":"..\/..\/images\/wolf-children.jpg",
			"slug":"wolf-children"
		},
		{
			"title":"Whisper of the Heart",
			"gatsby_image_path":"..\/..\/images\/whisper-of-the-heart.jpg",
			"slug":"whisper-of-the-heart"
		},
		{
			"title":"When Marnie Was There",
			"gatsby_image_path":"..\/..\/images\/when-marnie-was-there.jpg",
			"slug":"when-marnie-was-there"
		},
		{
			"title":"Weathering with You",
			"gatsby_image_path":"..\/..\/images\/weathering-with-you.jpg",
			"slug":"weathering-with-you"
		}
	],
	"related_by_poster":[
		{
			"title":"The Boy and the Beast",
			"gatsby_image_path":"..\/..\/images\/the-boy-and-the-beast.jpg",
			"slug":"the-boy-and-the-beast"
		},
		{
			"title":"Legally Blondes",
			"gatsby_image_path":"..\/..\/images\/legally-blondes.jpg",
			"slug":"legally-blondes"
		},
		{
			"title":"Zack and Miri Make a Porno",
			"gatsby_image_path":"..\/..\/images\/zack-and-miri-make-a-porno.jpg",
			"slug":"zack-and-miri-make-a-porno"
		},
		{
			"title":"Life As We Know It",
			"gatsby_image_path":"..\/..\/images\/life-as-we-know-it.jpg",
			"slug":"life-as-we-know-it"
		},
		{
			"title":"I Love You, Stupid",
			"gatsby_image_path":"..\/..\/images\/i-love-you-stupid.jpg",
			"slug":"i-love-you-stupid"
		},
		{
			"title":"Christmas with the Kranks",
			"gatsby_image_path":"..\/..\/images\/christmas-with-the-kranks.jpg",
			"slug":"christmas-with-the-kranks"
		},
		{
			"title":"Tad, the Lost Explorer",
			"gatsby_image_path":"..\/..\/images\/tad-the-lost-explorer.jpg",
			"slug":"tad-the-lost-explorer"
		},
		{
			"title":"Wild Child",
			"gatsby_image_path":"..\/..\/images\/wild-child.jpg",
			"slug":"wild-child"
		},
		{
			"title":"One Day",
			"gatsby_image_path":"..\/..\/images\/one-day.jpg",
			"slug":"one-day"
		},
		{
			"title":"The Craft",
			"gatsby_image_path":"..\/..\/images\/the-craft.jpg",
			"slug":"the-craft"
		},
		{
			"title":"Goodbye World",
			"gatsby_image_path":"..\/..\/images\/goodbye-world.jpg",
			"slug":"goodbye-world"
		},
		{
			"title":"Sextuplets",
			"gatsby_image_path":"..\/..\/images\/sextuplets.jpg",
			"slug":"sextuplets"
		},
		{
			"title":"Little Big Mouth",
			"gatsby_image_path":"..\/..\/images\/little-big-mouth.jpg",
			"slug":"little-big-mouth"
		},
		{
			"title":"Vacation",
			"gatsby_image_path":"..\/..\/images\/vacation.jpg",
			"slug":"vacation"
		},
		{
			"title":"Chucky's Vacation Slides",
			"gatsby_image_path":"..\/..\/images\/chucky-s-vacation-slides.jpg",
			"slug":"chucky-s-vacation-slides"
		},
		{
			"title":"The Help",
			"gatsby_image_path":"..\/..\/images\/the-help.jpg",
			"slug":"the-help"
		},
		{
			"title":"Extraction",
			"gatsby_image_path":"..\/..\/images\/extraction.jpg",
			"slug":"extraction"
		},
		{
			"title":"There's Something About Mario",
			"gatsby_image_path":"..\/..\/images\/there-s-something-about-mario.jpg",
			"slug":"there-s-something-about-mario"
		},
		{
			"title":"Ghosts of War",
			"gatsby_image_path":"..\/..\/images\/ghosts-of-war.jpg",
			"slug":"ghosts-of-war"
		},
		{
			"title":"Next Avengers: Heroes of Tomorrow",
			"gatsby_image_path":"..\/..\/images\/next-avengers-heroes-of-tomorrow.jpg",
			"slug":"next-avengers-heroes-of-tomorrow"
		}
	],
	"related_by_overview":[
		{
			"title":"461 Days of Bento: A Promise Between Father and Son",
			"gatsby_image_path":"..\/..\/images\/461-days-of-bento-a-promise-between-father-and-son.jpg",
			"slug":"461-days-of-bento-a-promise-between-father-and-son"
		},
		{
			"title":"The Garden of Words",
			"gatsby_image_path":"..\/..\/images\/the-garden-of-words.jpg",
			"slug":"the-garden-of-words"
		},
		{
			"title":"Ride Your Wave",
			"gatsby_image_path":"..\/..\/images\/ride-your-wave.jpg",
			"slug":"ride-your-wave"
		},
		{
			"title":"Your Name.",
			"gatsby_image_path":"..\/..\/images\/your-name.jpg",
			"slug":"your-name"
		},
		{
			"title":"The Irregular at Magic High School: The Girl Who Summons the Stars",
			"gatsby_image_path":"..\/..\/images\/the-irregular-at-magic-high-school-the-girl-who-summons-the-stars.jpg",
			"slug":"the-irregular-at-magic-high-school-the-girl-who-summons-the-stars"
		},
		{
			"title":"Anoko no Toriko",
			"gatsby_image_path":"..\/..\/images\/anoko-no-toriko.jpg",
			"slug":"anoko-no-toriko"
		},
		{
			"title":"HK: Hentai Kamen 2 - Abnormal Crisis",
			"gatsby_image_path":"..\/..\/images\/hk-hentai-kamen-2-abnormal-crisis.jpg",
			"slug":"hk-hentai-kamen-2-abnormal-crisis"
		},
		{
			"title":"Rurouni Kenshin: The Beginning",
			"gatsby_image_path":"..\/..\/images\/rurouni-kenshin-the-beginning.jpg",
			"slug":"rurouni-kenshin-the-beginning"
		},
		{
			"title":"Rurouni Kenshin Part I: Origins",
			"gatsby_image_path":"..\/..\/images\/rurouni-kenshin-part-i-origins.jpg",
			"slug":"rurouni-kenshin-part-i-origins"
		},
		{
			"title":"The Boy and the Beast",
			"gatsby_image_path":"..\/..\/images\/the-boy-and-the-beast.jpg",
			"slug":"the-boy-and-the-beast"
		},
		{
			"title":"Love, Chunibyo & Other Delusions! Take On Me",
			"gatsby_image_path":"..\/..\/images\/love-chunibyo-other-delusions-take-on-me.jpg",
			"slug":"love-chunibyo-other-delusions-take-on-me"
		},
		{
			"title":"Urusei Yatsura: Only You",
			"gatsby_image_path":"..\/..\/images\/urusei-yatsura-only-you.jpg",
			"slug":"urusei-yatsura-only-you"
		},
		{
			"title":"Sekaiichi Hatsukoi Movie",
			"gatsby_image_path":"..\/..\/images\/sekaiichi-hatsukoi-movie.jpg",
			"slug":"sekaiichi-hatsukoi-movie"
		},
		{
			"title":"Weathering with You",
			"gatsby_image_path":"..\/..\/images\/weathering-with-you.jpg",
			"slug":"weathering-with-you"
		},
		{
			"title":"Doraemon: Nobita and the New Steel Troops: ~Winged Angels~",
			"gatsby_image_path":"..\/..\/images\/doraemon-nobita-and-the-new-steel-troops-winged-angels.jpg",
			"slug":"doraemon-nobita-and-the-new-steel-troops-winged-angels"
		},
		{
			"title":"Yes, No, or Maybe Half?",
			"gatsby_image_path":"..\/..\/images\/yes-no-or-maybe-half.jpg",
			"slug":"yes-no-or-maybe-half"
		},
		{
			"title":"Naruto the Movie: Legend of the Stone of Gelel",
			"gatsby_image_path":"..\/..\/images\/naruto-the-movie-legend-of-the-stone-of-gelel.jpg",
			"slug":"naruto-the-movie-legend-of-the-stone-of-gelel"
		},
		{
			"title":"Cencoroll Connect",
			"gatsby_image_path":"..\/..\/images\/cencoroll-connect.jpg",
			"slug":"cencoroll-connect"
		},
		{
			"title":"Ao Oni The Animation",
			"gatsby_image_path":"..\/..\/images\/ao-oni-the-animation.jpg",
			"slug":"ao-oni-the-animation"
		},
		{
			"title":"A Whisker Away",
			"gatsby_image_path":"..\/..\/images\/a-whisker-away.jpg",
			"slug":"a-whisker-away"
		}
	],
	"tmdb_id":378064,
	"keywords":[
		"deaf",
		"friendship",
		"high school",
		"bullying",
		"coming of age",
		"based on manga",
		"woman director",
		"sign languages",
		"anime",
		"japanese school"
	]
}