{
	"title":"Ghostheads",
	"status":"Released",
	"runtime":100,
	"revenue":0,
	"release_date":"2016-04-23",
	"production_countries":[
		"Canada",
		"United States of America"
	],
	"production_companies":[],
	"poster_path":"\/qCVJDQfXjoUeU5G8e1WNvNX9BW.jpg",
	"imdb_id":"tt4976984",
	"original_title":"Ghostheads",
	"overview":"Ghostheads is a documentary that explores the extreme side of the Ghostbusters fandom. Join us as we travel the world meeting extreme Ghostbusters fans. Every Ghosthead is unique. Every Franchise is its own. Every pop culture fandom should learn how to give back to the community.",
	"original_language":"en",
	"adult":false,
	"budget":0,
	"genres":[
		"Documentary"
	],
	"keywords":[
		"ghostbuster",
		"cosplay",
		"cult following"
	],
	"tmdb_id":"367816",
	"slug":"ghostheads",
	"gatsby_image_path":"..\/..\/images\/ghostheads.jpg",
	"cast":[
		"Robin Shelby",
		"Dan Aykroyd",
		"Sigourney Weaver",
		"Ivan Reitman",
		"Paul Feig",
		"Ernie Hudson",
		"William Atherton",
		"Ray Parker, Jr."
	],
	"crew":[
		"Tommy Avallone",
		"Brenden Mertens",
		"Brenden Mertens",
		"Brenden Mertens",
		"Lee Leshen",
		"Derrick Kunzer"
	],
	"related_by_cast":[
		{
			"title":"Ghostbusters",
			"gatsby_image_path":"..\/..\/images\/ghostbusters-1984-06-08.jpg",
			"slug":"ghostbusters-1984-06-08"
		},
		{
			"title":"Ghostbusters II",
			"gatsby_image_path":"..\/..\/images\/ghostbusters-ii.jpg",
			"slug":"ghostbusters-ii"
		},
		{
			"title":"Ghostbusters: Afterlife",
			"gatsby_image_path":"..\/..\/images\/ghostbusters-afterlife.jpg",
			"slug":"ghostbusters-afterlife"
		},
		{
			"title":"WALL·E",
			"gatsby_image_path":"..\/..\/images\/wall-e.jpg",
			"slug":"wall-e"
		},
		{
			"title":"The Substitute",
			"gatsby_image_path":"..\/..\/images\/the-substitute.jpg",
			"slug":"the-substitute"
		},
		{
			"title":"The Cabin in the Woods",
			"gatsby_image_path":"..\/..\/images\/the-cabin-in-the-woods.jpg",
			"slug":"the-cabin-in-the-woods"
		},
		{
			"title":"Redemption Day",
			"gatsby_image_path":"..\/..\/images\/redemption-day.jpg",
			"slug":"redemption-day"
		},
		{
			"title":"Pixels",
			"gatsby_image_path":"..\/..\/images\/pixels.jpg",
			"slug":"pixels"
		},
		{
			"title":"My Salinger Year",
			"gatsby_image_path":"..\/..\/images\/my-salinger-year.jpg",
			"slug":"my-salinger-year"
		},
		{
			"title":"God's Not Dead 2",
			"gatsby_image_path":"..\/..\/images\/god-s-not-dead-2.jpg",
			"slug":"god-s-not-dead-2"
		},
		{
			"title":"Exodus: Gods and Kings",
			"gatsby_image_path":"..\/..\/images\/exodus-gods-and-kings.jpg",
			"slug":"exodus-gods-and-kings"
		},
		{
			"title":"Dragonball Evolution",
			"gatsby_image_path":"..\/..\/images\/dragonball-evolution.jpg",
			"slug":"dragonball-evolution"
		},
		{
			"title":"Die Hard",
			"gatsby_image_path":"..\/..\/images\/die-hard.jpg",
			"slug":"die-hard"
		},
		{
			"title":"Christmas with the Kranks",
			"gatsby_image_path":"..\/..\/images\/christmas-with-the-kranks.jpg",
			"slug":"christmas-with-the-kranks"
		},
		{
			"title":"Chappie",
			"gatsby_image_path":"..\/..\/images\/chappie.jpg",
			"slug":"chappie"
		},
		{
			"title":"Beverly Hills Chihuahua 3: Viva la Fiesta!",
			"gatsby_image_path":"..\/..\/images\/beverly-hills-chihuahua-3-viva-la-fiesta.jpg",
			"slug":"beverly-hills-chihuahua-3-viva-la-fiesta"
		},
		{
			"title":"Avatar",
			"gatsby_image_path":"..\/..\/images\/avatar.jpg",
			"slug":"avatar"
		},
		{
			"title":"Avatar 2",
			"gatsby_image_path":"..\/..\/images\/avatar-2.jpg",
			"slug":"avatar-2"
		},
		{
			"title":"Aliens",
			"gatsby_image_path":"..\/..\/images\/aliens.jpg",
			"slug":"aliens"
		},
		{
			"title":"Alien",
			"gatsby_image_path":"..\/..\/images\/alien.jpg",
			"slug":"alien"
		}
	],
	"related_by_overview":[
		{
			"title":"The Monuments Men",
			"gatsby_image_path":"..\/..\/images\/the-monuments-men.jpg",
			"slug":"the-monuments-men"
		},
		{
			"title":"War Dogs",
			"gatsby_image_path":"..\/..\/images\/war-dogs.jpg",
			"slug":"war-dogs"
		},
		{
			"title":"Money Heist: The Phenomenon",
			"gatsby_image_path":"..\/..\/images\/money-heist-the-phenomenon.jpg",
			"slug":"money-heist-the-phenomenon"
		},
		{
			"title":"Paranormal Activity",
			"gatsby_image_path":"..\/..\/images\/paranormal-activity.jpg",
			"slug":"paranormal-activity"
		},
		{
			"title":"Straight Outta Compton",
			"gatsby_image_path":"..\/..\/images\/straight-outta-compton.jpg",
			"slug":"straight-outta-compton"
		},
		{
			"title":"Soul Surfer",
			"gatsby_image_path":"..\/..\/images\/soul-surfer.jpg",
			"slug":"soul-surfer"
		},
		{
			"title":"Top Gun",
			"gatsby_image_path":"..\/..\/images\/top-gun.jpg",
			"slug":"top-gun"
		},
		{
			"title":"After Porn Ends",
			"gatsby_image_path":"..\/..\/images\/after-porn-ends.jpg",
			"slug":"after-porn-ends"
		},
		{
			"title":"Silk Road",
			"gatsby_image_path":"..\/..\/images\/silk-road.jpg",
			"slug":"silk-road"
		},
		{
			"title":"Convergence: Courage in a Crisis",
			"gatsby_image_path":"..\/..\/images\/convergence-courage-in-a-crisis.jpg",
			"slug":"convergence-courage-in-a-crisis"
		},
		{
			"title":"Out of Death",
			"gatsby_image_path":"..\/..\/images\/out-of-death.jpg",
			"slug":"out-of-death"
		},
		{
			"title":"Found",
			"gatsby_image_path":"..\/..\/images\/found.jpg",
			"slug":"found"
		},
		{
			"title":"I Am All Girls",
			"gatsby_image_path":"..\/..\/images\/i-am-all-girls.jpg",
			"slug":"i-am-all-girls"
		},
		{
			"title":"The Boss Baby: Get That Baby!",
			"gatsby_image_path":"..\/..\/images\/the-boss-baby-get-that-baby.jpg",
			"slug":"the-boss-baby-get-that-baby"
		},
		{
			"title":"The Hustle",
			"gatsby_image_path":"..\/..\/images\/the-hustle.jpg",
			"slug":"the-hustle"
		},
		{
			"title":"Suspiria",
			"gatsby_image_path":"..\/..\/images\/suspiria.jpg",
			"slug":"suspiria"
		},
		{
			"title":"Moxie",
			"gatsby_image_path":"..\/..\/images\/moxie.jpg",
			"slug":"moxie"
		},
		{
			"title":"Sweat",
			"gatsby_image_path":"..\/..\/images\/sweat.jpg",
			"slug":"sweat"
		},
		{
			"title":"The Lego Movie 2: The Second Part",
			"gatsby_image_path":"..\/..\/images\/the-lego-movie-2-the-second-part.jpg",
			"slug":"the-lego-movie-2-the-second-part"
		},
		{
			"title":"Impractical Jokers: The Movie",
			"gatsby_image_path":"..\/..\/images\/impractical-jokers-the-movie.jpg",
			"slug":"impractical-jokers-the-movie"
		}
	],
	"related_most_similar":[
		{
			"title":"Ghostbusters: Afterlife",
			"gatsby_image_path":"..\/..\/images\/ghostbusters-afterlife.jpg",
			"slug":"ghostbusters-afterlife"
		},
		{
			"title":"Ghostbusters",
			"gatsby_image_path":"..\/..\/images\/ghostbusters-1984-06-08.jpg",
			"slug":"ghostbusters-1984-06-08"
		},
		{
			"title":"Ghostbusters II",
			"gatsby_image_path":"..\/..\/images\/ghostbusters-ii.jpg",
			"slug":"ghostbusters-ii"
		},
		{
			"title":"Ghostbusters",
			"gatsby_image_path":"..\/..\/images\/ghostbusters.jpg",
			"slug":"ghostbusters"
		},
		{
			"title":"The Heat",
			"gatsby_image_path":"..\/..\/images\/the-heat.jpg",
			"slug":"the-heat"
		},
		{
			"title":"No Strings Attached",
			"gatsby_image_path":"..\/..\/images\/no-strings-attached.jpg",
			"slug":"no-strings-attached"
		},
		{
			"title":"xXx: Return of Xander Cage",
			"gatsby_image_path":"..\/..\/images\/xxx-return-of-xander-cage.jpg",
			"slug":"xxx-return-of-xander-cage"
		},
		{
			"title":"Woody Woodpecker",
			"gatsby_image_path":"..\/..\/images\/woody-woodpecker.jpg",
			"slug":"woody-woodpecker"
		},
		{
			"title":"Warning",
			"gatsby_image_path":"..\/..\/images\/warning.jpg",
			"slug":"warning"
		},
		{
			"title":"War for the Planet of the Apes",
			"gatsby_image_path":"..\/..\/images\/war-for-the-planet-of-the-apes.jpg",
			"slug":"war-for-the-planet-of-the-apes"
		},
		{
			"title":"Warcraft",
			"gatsby_image_path":"..\/..\/images\/warcraft.jpg",
			"slug":"warcraft"
		},
		{
			"title":"WALL·E",
			"gatsby_image_path":"..\/..\/images\/wall-e.jpg",
			"slug":"wall-e"
		},
		{
			"title":"Valerian and the City of a Thousand Planets",
			"gatsby_image_path":"..\/..\/images\/valerian-and-the-city-of-a-thousand-planets.jpg",
			"slug":"valerian-and-the-city-of-a-thousand-planets"
		},
		{
			"title":"Upside-Down Magic",
			"gatsby_image_path":"..\/..\/images\/upside-down-magic.jpg",
			"slug":"upside-down-magic"
		},
		{
			"title":"Transformers: The Last Knight",
			"gatsby_image_path":"..\/..\/images\/transformers-the-last-knight.jpg",
			"slug":"transformers-the-last-knight"
		},
		{
			"title":"Transformers: Rise of the Beasts",
			"gatsby_image_path":"..\/..\/images\/transformers-rise-of-the-beasts.jpg",
			"slug":"transformers-rise-of-the-beasts"
		},
		{
			"title":"Total Recall",
			"gatsby_image_path":"..\/..\/images\/total-recall.jpg",
			"slug":"total-recall"
		},
		{
			"title":"Tooth Fairy",
			"gatsby_image_path":"..\/..\/images\/tooth-fairy.jpg",
			"slug":"tooth-fairy"
		},
		{
			"title":"Those Who Wish Me Dead",
			"gatsby_image_path":"..\/..\/images\/those-who-wish-me-dead.jpg",
			"slug":"those-who-wish-me-dead"
		},
		{
			"title":"Thir13en Ghosts",
			"gatsby_image_path":"..\/..\/images\/thir13en-ghosts.jpg",
			"slug":"thir13en-ghosts"
		}
	],
	"related_by_poster":[
		{
			"title":"Naruto Shippuden the Movie: The Lost Tower",
			"gatsby_image_path":"..\/..\/images\/naruto-shippuden-the-movie-the-lost-tower.jpg",
			"slug":"naruto-shippuden-the-movie-the-lost-tower"
		},
		{
			"title":"Peçanha Contra o Animal",
			"gatsby_image_path":"..\/..\/images\/peçanha-contra-o-animal.jpg",
			"slug":"peçanha-contra-o-animal"
		},
		{
			"title":"Superman: Man of Tomorrow",
			"gatsby_image_path":"..\/..\/images\/superman-man-of-tomorrow.jpg",
			"slug":"superman-man-of-tomorrow"
		},
		{
			"title":"Jingle Jangle: A Christmas Journey",
			"gatsby_image_path":"..\/..\/images\/jingle-jangle-a-christmas-journey.jpg",
			"slug":"jingle-jangle-a-christmas-journey"
		},
		{
			"title":"Justice League vs. Teen Titans",
			"gatsby_image_path":"..\/..\/images\/justice-league-vs.-teen-titans.jpg",
			"slug":"justice-league-vs.-teen-titans"
		},
		{
			"title":"Night at the Museum: Battle of the Smithsonian",
			"gatsby_image_path":"..\/..\/images\/night-at-the-museum-battle-of-the-smithsonian.jpg",
			"slug":"night-at-the-museum-battle-of-the-smithsonian"
		},
		{
			"title":"The Mortuary Collection",
			"gatsby_image_path":"..\/..\/images\/the-mortuary-collection.jpg",
			"slug":"the-mortuary-collection"
		},
		{
			"title":"Dragon Ball: Yo! Son Goku and His Friends Return!!",
			"gatsby_image_path":"..\/..\/images\/dragon-ball-yo-son-goku-and-his-friends-return.jpg",
			"slug":"dragon-ball-yo-son-goku-and-his-friends-return"
		},
		{
			"title":"Black Fox",
			"gatsby_image_path":"..\/..\/images\/black-fox.jpg",
			"slug":"black-fox"
		},
		{
			"title":"Batman: Death in the Family",
			"gatsby_image_path":"..\/..\/images\/batman-death-in-the-family.jpg",
			"slug":"batman-death-in-the-family"
		},
		{
			"title":"Teenage Mutant Ninja Turtles: Out of the Shadows",
			"gatsby_image_path":"..\/..\/images\/teenage-mutant-ninja-turtles-out-of-the-shadows.jpg",
			"slug":"teenage-mutant-ninja-turtles-out-of-the-shadows"
		},
		{
			"title":"Ghosts of War",
			"gatsby_image_path":"..\/..\/images\/ghosts-of-war.jpg",
			"slug":"ghosts-of-war"
		},
		{
			"title":"Grisaia: Phantom Trigger The Animation",
			"gatsby_image_path":"..\/..\/images\/grisaia-phantom-trigger-the-animation.jpg",
			"slug":"grisaia-phantom-trigger-the-animation"
		},
		{
			"title":"Astro Boy",
			"gatsby_image_path":"..\/..\/images\/astro-boy.jpg",
			"slug":"astro-boy"
		},
		{
			"title":"Justice League: Gods and Monsters",
			"gatsby_image_path":"..\/..\/images\/justice-league-gods-and-monsters.jpg",
			"slug":"justice-league-gods-and-monsters"
		},
		{
			"title":"Sword Art Online: The Movie - Ordinal Scale",
			"gatsby_image_path":"..\/..\/images\/sword-art-online-the-movie-ordinal-scale.jpg",
			"slug":"sword-art-online-the-movie-ordinal-scale"
		},
		{
			"title":"Real Steel",
			"gatsby_image_path":"..\/..\/images\/real-steel.jpg",
			"slug":"real-steel"
		},
		{
			"title":"Naruto Shippuden the Movie: The Will of Fire",
			"gatsby_image_path":"..\/..\/images\/naruto-shippuden-the-movie-the-will-of-fire.jpg",
			"slug":"naruto-shippuden-the-movie-the-will-of-fire"
		},
		{
			"title":"Jujutsu Kaisen 0: The Movie",
			"gatsby_image_path":"..\/..\/images\/jujutsu-kaisen-0-the-movie.jpg",
			"slug":"jujutsu-kaisen-0-the-movie"
		},
		{
			"title":"Muppets Haunted Mansion",
			"gatsby_image_path":"..\/..\/images\/muppets-haunted-mansion.jpg",
			"slug":"muppets-haunted-mansion"
		}
	],
	"tmdb_popularity":52
}