{
	"title":"Ghost Rider",
	"status":"Released",
	"runtime":114,
	"revenue":228738393,
	"release_date":"2007-02-16",
	"production_countries":[
		"United States of America",
		"Australia"
	],
	"production_companies":[
		"Crystal Sky Pictures",
		"Relativity Media",
		"Michael De Luca Productions",
		"GH One",
		"Vengeance Productions Pty. Ltd.",
		"Columbia Pictures",
		"Marvel Studios"
	],
	"poster_path":"\/1pyU94dAY7npDQCKuxCSyX9KthN.jpg",
	"imdb_id":"tt0259324",
	"original_title":"Ghost Rider",
	"overview":"In order to save his dying father, young stunt cyclist Johnny Blaze sells his soul to Mephistopheles and sadly parts from the pure-hearted Roxanne Simpson, the love of his life. Years later, Johnny's path crosses again with Roxanne, now a go-getting reporter, and also with Mephistopheles, who offers to release Johnny's soul if Johnny becomes the fabled, fiery 'Ghost Rider'.",
	"original_language":"en",
	"adult":false,
	"budget":110000000,
	"genres":[
		"Thriller",
		"Action",
		"Fantasy"
	],
	"slug":"ghost-rider",
	"gatsby_image_path":"..\/..\/images\/ghost-rider.jpg",
	"cast":[
		"Nicolas Cage",
		"Eva Mendes",
		"Sam Elliott",
		"Wes Bentley",
		"Peter Fonda",
		"Matt Long",
		"Brett Cullen",
		"Raquel Alessi",
		"Donal Logue",
		"Tony Ghosthawk"
	],
	"crew":[
		"Jeanne McCarthy",
		"David S. Goyer",
		"Richard Francis-Bruce",
		"Michael De Luca",
		"Stan Lee",
		"Avi Arad",
		"Christopher Young",
		"Peter Russell",
		"Lisa Brennan",
		"Dane A. Davis"
	],
	"related_by_cast":[
		{
			"title":"Willy's Wonderland",
			"gatsby_image_path":"..\/..\/images\/willy-s-wonderland.jpg",
			"slug":"willy-s-wonderland"
		},
		{
			"title":"The Good Dinosaur",
			"gatsby_image_path":"..\/..\/images\/the-good-dinosaur.jpg",
			"slug":"the-good-dinosaur"
		},
		{
			"title":"The Croods",
			"gatsby_image_path":"..\/..\/images\/the-croods.jpg",
			"slug":"the-croods"
		},
		{
			"title":"The Croods: A New Age",
			"gatsby_image_path":"..\/..\/images\/the-croods-a-new-age.jpg",
			"slug":"the-croods-a-new-age"
		},
		{
			"title":"Snake Eyes",
			"gatsby_image_path":"..\/..\/images\/snake-eyes.jpg",
			"slug":"snake-eyes"
		},
		{
			"title":"Primal",
			"gatsby_image_path":"..\/..\/images\/primal.jpg",
			"slug":"primal"
		},
		{
			"title":"Pig",
			"gatsby_image_path":"..\/..\/images\/pig.jpg",
			"slug":"pig"
		},
		{
			"title":"P2",
			"gatsby_image_path":"..\/..\/images\/p2.jpg",
			"slug":"p2"
		},
		{
			"title":"Mission: Impossible - Fallout",
			"gatsby_image_path":"..\/..\/images\/mission-impossible-fallout.jpg",
			"slug":"mission-impossible-fallout"
		},
		{
			"title":"Mandy",
			"gatsby_image_path":"..\/..\/images\/mandy.jpg",
			"slug":"mandy"
		}
	],
	"related_most_similar":[
		{
			"title":"Ghost Rider: Spirit of Vengeance",
			"gatsby_image_path":"..\/..\/images\/ghost-rider-spirit-of-vengeance.jpg",
			"slug":"ghost-rider-spirit-of-vengeance"
		},
		{
			"title":"Thor",
			"gatsby_image_path":"..\/..\/images\/thor.jpg",
			"slug":"thor"
		},
		{
			"title":"The Amazing Spider-Man 2",
			"gatsby_image_path":"..\/..\/images\/the-amazing-spider-man-2.jpg",
			"slug":"the-amazing-spider-man-2"
		},
		{
			"title":"Spider-Man: Into the Spider-Verse",
			"gatsby_image_path":"..\/..\/images\/spider-man-into-the-spider-verse.jpg",
			"slug":"spider-man-into-the-spider-verse"
		},
		{
			"title":"Spider-Man: Homecoming",
			"gatsby_image_path":"..\/..\/images\/spider-man-homecoming.jpg",
			"slug":"spider-man-homecoming"
		},
		{
			"title":"Spider-Man: Far From Home",
			"gatsby_image_path":"..\/..\/images\/spider-man-far-from-home.jpg",
			"slug":"spider-man-far-from-home"
		},
		{
			"title":"Spider-Man 3",
			"gatsby_image_path":"..\/..\/images\/spider-man-3.jpg",
			"slug":"spider-man-3"
		},
		{
			"title":"Thor: Ragnarok",
			"gatsby_image_path":"..\/..\/images\/thor-ragnarok.jpg",
			"slug":"thor-ragnarok"
		},
		{
			"title":"The Incredible Hulk",
			"gatsby_image_path":"..\/..\/images\/the-incredible-hulk.jpg",
			"slug":"the-incredible-hulk"
		},
		{
			"title":"The Amazing Spider-Man",
			"gatsby_image_path":"..\/..\/images\/the-amazing-spider-man.jpg",
			"slug":"the-amazing-spider-man"
		}
	],
	"related_by_poster":[
		{
			"title":"The Last Samurai",
			"gatsby_image_path":"..\/..\/images\/the-last-samurai.jpg",
			"slug":"the-last-samurai"
		},
		{
			"title":"Hell on the Border",
			"gatsby_image_path":"..\/..\/images\/hell-on-the-border.jpg",
			"slug":"hell-on-the-border"
		},
		{
			"title":"Sacrifice",
			"gatsby_image_path":"..\/..\/images\/sacrifice.jpg",
			"slug":"sacrifice"
		},
		{
			"title":"War of the Worlds",
			"gatsby_image_path":"..\/..\/images\/war-of-the-worlds.jpg",
			"slug":"war-of-the-worlds"
		},
		{
			"title":"Samson",
			"gatsby_image_path":"..\/..\/images\/samson.jpg",
			"slug":"samson"
		},
		{
			"title":"Kingsglaive: Final Fantasy XV",
			"gatsby_image_path":"..\/..\/images\/kingsglaive-final-fantasy-xv.jpg",
			"slug":"kingsglaive-final-fantasy-xv"
		},
		{
			"title":"The Amityville Horror",
			"gatsby_image_path":"..\/..\/images\/the-amityville-horror.jpg",
			"slug":"the-amityville-horror"
		},
		{
			"title":"Wolf Warrior 2",
			"gatsby_image_path":"..\/..\/images\/wolf-warrior-2.jpg",
			"slug":"wolf-warrior-2"
		},
		{
			"title":"The Expendables 2",
			"gatsby_image_path":"..\/..\/images\/the-expendables-2.jpg",
			"slug":"the-expendables-2"
		},
		{
			"title":"Star Wars: The Force Awakens",
			"gatsby_image_path":"..\/..\/images\/star-wars-the-force-awakens.jpg",
			"slug":"star-wars-the-force-awakens"
		},
		{
			"title":"The Mortal Instruments: City of Bones",
			"gatsby_image_path":"..\/..\/images\/the-mortal-instruments-city-of-bones.jpg",
			"slug":"the-mortal-instruments-city-of-bones"
		},
		{
			"title":"The Unfamiliar",
			"gatsby_image_path":"..\/..\/images\/the-unfamiliar.jpg",
			"slug":"the-unfamiliar"
		},
		{
			"title":"Backdraft 2",
			"gatsby_image_path":"..\/..\/images\/backdraft-2.jpg",
			"slug":"backdraft-2"
		},
		{
			"title":"Annihilation",
			"gatsby_image_path":"..\/..\/images\/annihilation.jpg",
			"slug":"annihilation"
		},
		{
			"title":"The Mummy Returns",
			"gatsby_image_path":"..\/..\/images\/the-mummy-returns.jpg",
			"slug":"the-mummy-returns"
		},
		{
			"title":"Se7en",
			"gatsby_image_path":"..\/..\/images\/se7en.jpg",
			"slug":"se7en"
		},
		{
			"title":"Ellipse",
			"gatsby_image_path":"..\/..\/images\/ellipse.jpg",
			"slug":"ellipse"
		},
		{
			"title":"Scorched Earth",
			"gatsby_image_path":"..\/..\/images\/scorched-earth.jpg",
			"slug":"scorched-earth"
		},
		{
			"title":"The Mummy",
			"gatsby_image_path":"..\/..\/images\/the-mummy.jpg",
			"slug":"the-mummy"
		},
		{
			"title":"The Red Sea Diving Resort",
			"gatsby_image_path":"..\/..\/images\/the-red-sea-diving-resort.jpg",
			"slug":"the-red-sea-diving-resort"
		}
	]
}