{
	"title":"La Llorona",
	"status":"Released",
	"runtime":97,
	"revenue":0,
	"release_date":"2020-01-22",
	"production_countries":[
		"Guatemala",
		"France"
	],
	"production_companies":[
		"La Casa de Producción",
		"Les Films du Volcan",
		"L'Aide aux Cinémas du Monde",
		"Film Factory"
	],
	"poster_path":"\/lIMrT43BRAXWxtSAtj7Kc0awgVT.jpg",
	"imdb_id":"tt10767168",
	"original_title":"La Llorona",
	"overview":"Accused of the genocide of Mayan people, retired general Enrique is trapped in his mansion by massive protests. Abandoned by his staff, the indignant old man and his family must face the devastating truth of his actions and the growing sense that a wrathful supernatural force is targeting them for his crimes.",
	"original_language":"es",
	"adult":false,
	"budget":0,
	"genres":[
		"Thriller",
		"Horror",
		"Drama"
	],
	"slug":"la-llorona",
	"gatsby_image_path":"..\/..\/images\/la-llorona.jpg",
	"cast":[
		"María Mercedes Coroy",
		"Sabrina De La Hoz",
		"Margarita Kénefic",
		"Julio Díaz",
		"María Telón",
		"Juan Pablo Olyslager",
		"Ayla-Elea Hurtado",
		"Pedro Javier Silva Lira"
	],
	"crew":[
		"Pascual Reyes",
		"Herminio Gutiérrez",
		"Jayro Bustamante",
		"Jayro Bustamante",
		"Jayro Bustamante",
		"Jayro Bustamante",
		"Marina Peralta",
		"Eduardo Cáceres",
		"Nicolás Wong",
		"Sebastián Muñoz"
	],
	"related_by_cast":[
		{
			"title":"Zootopia",
			"gatsby_image_path":"..\/..\/images\/zootopia.jpg",
			"slug":"zootopia"
		},
		{
			"title":"Zone 414",
			"gatsby_image_path":"..\/..\/images\/zone-414.jpg",
			"slug":"zone-414"
		},
		{
			"title":"Zombieland",
			"gatsby_image_path":"..\/..\/images\/zombieland.jpg",
			"slug":"zombieland"
		},
		{
			"title":"Zombieland: Double Tap",
			"gatsby_image_path":"..\/..\/images\/zombieland-double-tap.jpg",
			"slug":"zombieland-double-tap"
		},
		{
			"title":"Zathura: A Space Adventure",
			"gatsby_image_path":"..\/..\/images\/zathura-a-space-adventure.jpg",
			"slug":"zathura-a-space-adventure"
		},
		{
			"title":"Zack Snyder's Justice League",
			"gatsby_image_path":"..\/..\/images\/zack-snyder-s-justice-league.jpg",
			"slug":"zack-snyder-s-justice-league"
		},
		{
			"title":"Zack and Miri Make a Porno",
			"gatsby_image_path":"..\/..\/images\/zack-and-miri-make-a-porno.jpg",
			"slug":"zack-and-miri-make-a-porno"
		},
		{
			"title":"Yu-Gi-Oh!: The Dark Side of Dimensions",
			"gatsby_image_path":"..\/..\/images\/yu-gi-oh-the-dark-side-of-dimensions.jpg",
			"slug":"yu-gi-oh-the-dark-side-of-dimensions"
		},
		{
			"title":"Your Name.",
			"gatsby_image_path":"..\/..\/images\/your-name.jpg",
			"slug":"your-name"
		},
		{
			"title":"Young Sister-in-law 3 - 2019",
			"gatsby_image_path":"..\/..\/images\/young-sister-in-law-3-2019.jpg",
			"slug":"young-sister-in-law-3-2019"
		},
		{
			"title":"Young and Wild",
			"gatsby_image_path":"..\/..\/images\/young-and-wild.jpg",
			"slug":"young-and-wild"
		},
		{
			"title":"Yes, No, or Maybe Half?",
			"gatsby_image_path":"..\/..\/images\/yes-no-or-maybe-half.jpg",
			"slug":"yes-no-or-maybe-half"
		},
		{
			"title":"Yes Man",
			"gatsby_image_path":"..\/..\/images\/yes-man.jpg",
			"slug":"yes-man"
		},
		{
			"title":"Yes Day",
			"gatsby_image_path":"..\/..\/images\/yes-day.jpg",
			"slug":"yes-day"
		},
		{
			"title":"Year One",
			"gatsby_image_path":"..\/..\/images\/year-one.jpg",
			"slug":"year-one"
		},
		{
			"title":"Yara",
			"gatsby_image_path":"..\/..\/images\/yara.jpg",
			"slug":"yara"
		},
		{
			"title":"xXx: Return of Xander Cage",
			"gatsby_image_path":"..\/..\/images\/xxx-return-of-xander-cage.jpg",
			"slug":"xxx-return-of-xander-cage"
		},
		{
			"title":"Xtreme",
			"gatsby_image_path":"..\/..\/images\/xtreme.jpg",
			"slug":"xtreme"
		},
		{
			"title":"X-Men: Days of Future Past",
			"gatsby_image_path":"..\/..\/images\/x-men-days-of-future-past.jpg",
			"slug":"x-men-days-of-future-past"
		},
		{
			"title":"X-Men: Apocalypse",
			"gatsby_image_path":"..\/..\/images\/x-men-apocalypse.jpg",
			"slug":"x-men-apocalypse"
		}
	],
	"related_most_similar":[
		{
			"title":"Titane",
			"gatsby_image_path":"..\/..\/images\/titane.jpg",
			"slug":"titane"
		},
		{
			"title":"The Orphanage",
			"gatsby_image_path":"..\/..\/images\/the-orphanage.jpg",
			"slug":"the-orphanage"
		},
		{
			"title":"Fever Dream",
			"gatsby_image_path":"..\/..\/images\/fever-dream.jpg",
			"slug":"fever-dream"
		},
		{
			"title":"Don't Listen",
			"gatsby_image_path":"..\/..\/images\/don-t-listen.jpg",
			"slug":"don-t-listen"
		},
		{
			"title":"Cell 211",
			"gatsby_image_path":"..\/..\/images\/cell-211.jpg",
			"slug":"cell-211"
		},
		{
			"title":"World War Z",
			"gatsby_image_path":"..\/..\/images\/world-war-z.jpg",
			"slug":"world-war-z"
		},
		{
			"title":"What Happened to Monday",
			"gatsby_image_path":"..\/..\/images\/what-happened-to-monday.jpg",
			"slug":"what-happened-to-monday"
		},
		{
			"title":"Tokyo Ghoul",
			"gatsby_image_path":"..\/..\/images\/tokyo-ghoul.jpg",
			"slug":"tokyo-ghoul"
		},
		{
			"title":"Time Share",
			"gatsby_image_path":"..\/..\/images\/time-share.jpg",
			"slug":"time-share"
		},
		{
			"title":"The Ring Two",
			"gatsby_image_path":"..\/..\/images\/the-ring-two.jpg",
			"slug":"the-ring-two"
		},
		{
			"title":"The Rental",
			"gatsby_image_path":"..\/..\/images\/the-rental.jpg",
			"slug":"the-rental"
		},
		{
			"title":"The Purge",
			"gatsby_image_path":"..\/..\/images\/the-purge.jpg",
			"slug":"the-purge"
		},
		{
			"title":"The Purge: Election Year",
			"gatsby_image_path":"..\/..\/images\/the-purge-election-year.jpg",
			"slug":"the-purge-election-year"
		},
		{
			"title":"The Platform",
			"gatsby_image_path":"..\/..\/images\/the-platform.jpg",
			"slug":"the-platform"
		},
		{
			"title":"The Owners",
			"gatsby_image_path":"..\/..\/images\/the-owners.jpg",
			"slug":"the-owners"
		},
		{
			"title":"The Next Three Days",
			"gatsby_image_path":"..\/..\/images\/the-next-three-days.jpg",
			"slug":"the-next-three-days"
		},
		{
			"title":"The Mad Women's Ball",
			"gatsby_image_path":"..\/..\/images\/the-mad-women-s-ball.jpg",
			"slug":"the-mad-women-s-ball"
		},
		{
			"title":"The Invisible Guest",
			"gatsby_image_path":"..\/..\/images\/the-invisible-guest.jpg",
			"slug":"the-invisible-guest"
		},
		{
			"title":"The Hills Have Eyes",
			"gatsby_image_path":"..\/..\/images\/the-hills-have-eyes.jpg",
			"slug":"the-hills-have-eyes"
		},
		{
			"title":"The Exorcism of Emily Rose",
			"gatsby_image_path":"..\/..\/images\/the-exorcism-of-emily-rose.jpg",
			"slug":"the-exorcism-of-emily-rose"
		}
	],
	"related_by_poster":[
		{
			"title":"Honest Thief",
			"gatsby_image_path":"..\/..\/images\/honest-thief.jpg",
			"slug":"honest-thief"
		},
		{
			"title":"The BFG",
			"gatsby_image_path":"..\/..\/images\/the-bfg.jpg",
			"slug":"the-bfg"
		},
		{
			"title":"The Godfather",
			"gatsby_image_path":"..\/..\/images\/the-godfather.jpg",
			"slug":"the-godfather"
		},
		{
			"title":"Los viejos",
			"gatsby_image_path":"..\/..\/images\/los-viejos.jpg",
			"slug":"los-viejos"
		},
		{
			"title":"Chronicle",
			"gatsby_image_path":"..\/..\/images\/chronicle.jpg",
			"slug":"chronicle"
		},
		{
			"title":"Insidious: The Last Key",
			"gatsby_image_path":"..\/..\/images\/insidious-the-last-key.jpg",
			"slug":"insidious-the-last-key"
		},
		{
			"title":"Crank: High Voltage",
			"gatsby_image_path":"..\/..\/images\/crank-high-voltage.jpg",
			"slug":"crank-high-voltage"
		},
		{
			"title":"The Kill Team",
			"gatsby_image_path":"..\/..\/images\/the-kill-team.jpg",
			"slug":"the-kill-team"
		},
		{
			"title":"A Star Is Born",
			"gatsby_image_path":"..\/..\/images\/a-star-is-born.jpg",
			"slug":"a-star-is-born"
		},
		{
			"title":"Beyond White Space",
			"gatsby_image_path":"..\/..\/images\/beyond-white-space.jpg",
			"slug":"beyond-white-space"
		},
		{
			"title":"The Crossroads of Hunter Wilde",
			"gatsby_image_path":"..\/..\/images\/the-crossroads-of-hunter-wilde.jpg",
			"slug":"the-crossroads-of-hunter-wilde"
		},
		{
			"title":"Fifty Shades of Grey",
			"gatsby_image_path":"..\/..\/images\/fifty-shades-of-grey.jpg",
			"slug":"fifty-shades-of-grey"
		},
		{
			"title":"Legion",
			"gatsby_image_path":"..\/..\/images\/legion.jpg",
			"slug":"legion"
		},
		{
			"title":"The Legend of Tarzan",
			"gatsby_image_path":"..\/..\/images\/the-legend-of-tarzan.jpg",
			"slug":"the-legend-of-tarzan"
		},
		{
			"title":"Point Break",
			"gatsby_image_path":"..\/..\/images\/point-break.jpg",
			"slug":"point-break"
		},
		{
			"title":"Evangelion: 3.0+1.0 Thrice Upon a Time",
			"gatsby_image_path":"..\/..\/images\/evangelion-3.0-+1.0-thrice-upon-a-time.jpg",
			"slug":"evangelion-3.0-+1.0-thrice-upon-a-time"
		},
		{
			"title":"The 5th Wave",
			"gatsby_image_path":"..\/..\/images\/the-5th-wave.jpg",
			"slug":"the-5th-wave"
		},
		{
			"title":"The Viking War",
			"gatsby_image_path":"..\/..\/images\/the-viking-war.jpg",
			"slug":"the-viking-war"
		},
		{
			"title":"Breakthrough",
			"gatsby_image_path":"..\/..\/images\/breakthrough.jpg",
			"slug":"breakthrough"
		},
		{
			"title":"Blue Miracle",
			"gatsby_image_path":"..\/..\/images\/blue-miracle.jpg",
			"slug":"blue-miracle"
		}
	],
	"related_by_overview":[
		{
			"title":"Colombiana",
			"gatsby_image_path":"..\/..\/images\/colombiana.jpg",
			"slug":"colombiana"
		},
		{
			"title":"The Vault",
			"gatsby_image_path":"..\/..\/images\/the-vault.jpg",
			"slug":"the-vault"
		},
		{
			"title":"Cowboys & Aliens",
			"gatsby_image_path":"..\/..\/images\/cowboys-aliens.jpg",
			"slug":"cowboys-aliens"
		},
		{
			"title":"Leal",
			"gatsby_image_path":"..\/..\/images\/leal.jpg",
			"slug":"leal"
		},
		{
			"title":"Machete",
			"gatsby_image_path":"..\/..\/images\/machete.jpg",
			"slug":"machete"
		},
		{
			"title":"La Leyenda del Diamante",
			"gatsby_image_path":"..\/..\/images\/la-leyenda-del-diamante.jpg",
			"slug":"la-leyenda-del-diamante"
		},
		{
			"title":"Mama",
			"gatsby_image_path":"..\/..\/images\/mama.jpg",
			"slug":"mama"
		},
		{
			"title":"The Lion Guard: Return of the Roar",
			"gatsby_image_path":"..\/..\/images\/the-lion-guard-return-of-the-roar.jpg",
			"slug":"the-lion-guard-return-of-the-roar"
		},
		{
			"title":"Spy Kids 2: The Island of Lost Dreams",
			"gatsby_image_path":"..\/..\/images\/spy-kids-2-the-island-of-lost-dreams.jpg",
			"slug":"spy-kids-2-the-island-of-lost-dreams"
		},
		{
			"title":"The Immortal",
			"gatsby_image_path":"..\/..\/images\/the-immortal.jpg",
			"slug":"the-immortal"
		},
		{
			"title":"Special Forces",
			"gatsby_image_path":"..\/..\/images\/special-forces.jpg",
			"slug":"special-forces"
		},
		{
			"title":"Deep Blue Sea 3",
			"gatsby_image_path":"..\/..\/images\/deep-blue-sea-3.jpg",
			"slug":"deep-blue-sea-3"
		},
		{
			"title":"3-D Sex and Zen: Extreme Ecstasy",
			"gatsby_image_path":"..\/..\/images\/3-d-sex-and-zen-extreme-ecstasy.jpg",
			"slug":"3-d-sex-and-zen-extreme-ecstasy"
		},
		{
			"title":"Lokillo: Nothing's the Same",
			"gatsby_image_path":"..\/..\/images\/lokillo-nothing-s-the-same.jpg",
			"slug":"lokillo-nothing-s-the-same"
		},
		{
			"title":"Sicario",
			"gatsby_image_path":"..\/..\/images\/sicario.jpg",
			"slug":"sicario"
		},
		{
			"title":"Pirates of the Caribbean: On Stranger Tides",
			"gatsby_image_path":"..\/..\/images\/pirates-of-the-caribbean-on-stranger-tides.jpg",
			"slug":"pirates-of-the-caribbean-on-stranger-tides"
		},
		{
			"title":"Jeepers Creepers 2",
			"gatsby_image_path":"..\/..\/images\/jeepers-creepers-2.jpg",
			"slug":"jeepers-creepers-2"
		},
		{
			"title":"Land",
			"gatsby_image_path":"..\/..\/images\/land.jpg",
			"slug":"land"
		},
		{
			"title":"Revirginized",
			"gatsby_image_path":"..\/..\/images\/revirginized.jpg",
			"slug":"revirginized"
		},
		{
			"title":"Primal: Tales of Savagery",
			"gatsby_image_path":"..\/..\/images\/primal-tales-of-savagery.jpg",
			"slug":"primal-tales-of-savagery"
		}
	],
	"tmdb_id":617708,
	"keywords":[
		"dictator",
		"war crimes",
		"trial",
		"genocide",
		"guatemala",
		"historic",
		"war criminal",
		"indigenous peoples",
		"guatemalan civil war"
	]
}