{
	"title":"Malignant",
	"status":"Released",
	"runtime":112,
	"revenue":24640084,
	"release_date":"2021-09-01",
	"production_countries":[
		"China",
		"United States of America"
	],
	"production_companies":[
		"Warner Bros. Pictures",
		"New Line Cinema",
		"Starlight International Media",
		"Midas Innovation",
		"Atomic Monster",
		"BOOM! Studios"
	],
	"poster_path":"\/dGv2BWjzwAz6LB8a8JeRIZL8hSz.jpg",
	"imdb_id":"tt3811906",
	"original_title":"Malignant",
	"overview":"Madison is paralyzed by shocking visions of grisly murders, and her torment worsens as she discovers that these waking dreams are in fact terrifying realities with a mysterious tie to her past.",
	"original_language":"en",
	"adult":false,
	"budget":40000000,
	"genres":[
		"Horror",
		"Mystery",
		"Thriller"
	],
	"keywords":[
		"detective",
		"brain tumor",
		"monster",
		"dream",
		"seattle, usa",
		"murder",
		"gore",
		"vision",
		"serial killer",
		"hospital",
		"miscarriage",
		"videotape",
		"murder mystery",
		"sister sister relationship",
		"psychic connection"
	],
	"tmdb_id":"619778",
	"slug":"malignant",
	"gatsby_image_path":"..\/..\/images\/malignant.jpg",
	"cast":[
		"Annabelle Wallis",
		"Maddie Hasson",
		"George Young",
		"Michole Briana White",
		"Mckenna Grace",
		"Jacqueline McKenzie",
		"Jake Abel",
		"Ray Chase",
		"Jean Louisa Kelly",
		"Susanna Thompson"
	],
	"crew":[
		"Eric McLeod",
		"Sala Baker",
		"James Wan",
		"James Wan",
		"James Wan",
		"Joey Box",
		"Anne McCarthy",
		"Jennifer M. Gentile",
		"Odin Benitez",
		"Richard Brener"
	]
}