{
	"title":"No eres tú, soy yo",
	"status":"Released",
	"runtime":100,
	"revenue":0,
	"release_date":"2010-08-27",
	"production_countries":[
		"Mexico"
	],
	"production_companies":[
		"Warner Bros. Television",
		"Río Negro Producciones",
		"FIDECINE"
	],
	"poster_path":"\/tyjzgGRrBGbjyT13IRG7Sr8E1YK.jpg",
	"imdb_id":"tt1421046",
	"original_title":"No eres tú, soy yo",
	"overview":"Javier se ha casado con María, el amor de su vida, y ahora lo único que desea es estar feliz con ella el resto de su vida, pero el destino se la quita poco después de la boda. Ahora Javier está enredado en sus emociones: ¿cómo aceptará la muerte de su mujer para encontrar nuevamente el amor?",
	"original_language":"es",
	"adult":false,
	"budget":0,
	"genres":[
		"Drama",
		"Comedy",
		"Romance"
	],
	"keywords":[],
	"tmdb_id":"64694",
	"slug":"no-eres-tú-soy-yo",
	"gatsby_image_path":"..\/..\/images\/no-eres-tú-soy-yo.jpg",
	"cast":[
		"Eugenio Derbez",
		"Alejandra Barros",
		"Juan Ramírez",
		"Martina García"
	],
	"crew":[
		"Juan Taratuto",
		"Cecilia Dopazo",
		"Alejandro Springall",
		"Alejandro Springall",
		"Nadia Ayala Tabachnik",
		"Luis Aura"
	]
}