{
	"title":"Nussa",
	"status":"Released",
	"runtime":107,
	"revenue":0,
	"release_date":"2021-10-14",
	"production_countries":[
		"Indonesia"
	],
	"production_companies":[
		"The Little Giantz",
		"Visinema Pictures"
	],
	"poster_path":"\/grhplRFAr1CCa5VNcd9KUTE4aOo.jpg",
	"imdb_id":"tt11710090",
	"original_title":"Nussa",
	"overview":"Planning to impress his father who is coming home after being abroad for a year, Nussa the smart 9-year-old kid participates in his school’s science competition. But when he receives news that his father cancelled his trip home and is unable to attend the competition, and at the same time a new, smart student named Jonni quickly becomes his rival in the school's science competition, Nussa learns the true meaning of gratitude.",
	"original_language":"id",
	"adult":false,
	"budget":0,
	"genres":[
		"Animation",
		"Family"
	],
	"keywords":[],
	"tmdb_id":"681783",
	"slug":"nussa",
	"gatsby_image_path":"..\/..\/images\/nussa.jpg",
	"cast":[
		"Muzakki Ramdhan",
		"Aysha Razaana Ocean Fajar",
		"Ali Fikry",
		"Asri Welas",
		"Hamka Siregar",
		"Opie Kumis",
		"Raisa Andriana",
		"Maudy Koesnaedi",
		"Imam Darto",
		"Dewi Sandra"
	],
	"crew":[
		"Ryan Adriandhy",
		"Angga Dwimas Sasongko",
		"Anggia Kharisma",
		"Anggia Kharisma",
		"M. Irfan Ramli",
		"Ganda Hartadi",
		"Ofel Obaja",
		"Bony Wirasmono",
		"Bony Wirasmono",
		"Muhammad Nurman"
	]
}