{
	"title":"The Wedding Unplanner",
	"status":"Released",
	"runtime":110,
	"revenue":3069303,
	"release_date":"2020-02-14",
	"production_countries":[
		"Spain"
	],
	"production_companies":[
		"Atresmedia",
		"El Álamo Producciones Cinematográficas S.L."
	],
	"poster_path":"\/bkz7ZoqJMFziqF8yQzkmfMRUEG.jpg",
	"imdb_id":"tt9519642",
	"original_title":"Hasta que la boda nos separe",
	"overview":"Marina is a woman in her thirties who works organizing weddings. Not because she is an inveterate romantic just because, as she says, \"when people are in love, they don't care about money\". Unlike her customers, she enjoys a life without ties or commitments, until the moment when she falls in love with Carlos. The problem is not only he is about to get married, but also his fiancee is Marina's childhood friend and they have hired her as their Wedding Planner.",
	"original_language":"es",
	"adult":false,
	"budget":0,
	"genres":[
		"Comedy",
		"Romance"
	],
	"slug":"the-wedding-unplanner",
	"gatsby_image_path":"..\/..\/images\/the-wedding-unplanner.jpg",
	"cast":[
		"Belén Cuesta",
		"Álex García",
		"Adrián Lastra",
		"Silvia Alonso",
		"Pilar Calvo Morillas",
		"Antonio Resines",
		"Malena Alterio",
		"Jordi Sánchez",
		"Gracia Olayo",
		"Antonio Dechent"
	],
	"crew":[
		"Eduardo Campoy",
		"Mercedes Gamero",
		"Juana Martínez",
		"Mikel Lejarza",
		"Dani de la Orden",
		"Chechu Graf",
		"Olatz Arroyo",
		"Paloma Lozano",
		"Javier Fernández",
		"Rosa Pérez"
	],
	"related_by_cast":[
		{
			"title":"Solo una vez",
			"gatsby_image_path":"..\/..\/images\/solo-una-vez.jpg",
			"slug":"solo-una-vez"
		},
		{
			"title":"García y García",
			"gatsby_image_path":"..\/..\/images\/garcía-y-garcía.jpg",
			"slug":"garcía-y-garcía"
		},
		{
			"title":"Operación Camarón",
			"gatsby_image_path":"..\/..\/images\/operación-camarón.jpg",
			"slug":"operación-camarón"
		},
		{
			"title":"Cell 211",
			"gatsby_image_path":"..\/..\/images\/cell-211.jpg",
			"slug":"cell-211"
		},
		{
			"title":"Zootopia",
			"gatsby_image_path":"..\/..\/images\/zootopia.jpg",
			"slug":"zootopia"
		},
		{
			"title":"Zone 414",
			"gatsby_image_path":"..\/..\/images\/zone-414.jpg",
			"slug":"zone-414"
		},
		{
			"title":"Zombieland",
			"gatsby_image_path":"..\/..\/images\/zombieland.jpg",
			"slug":"zombieland"
		},
		{
			"title":"Zombieland: Double Tap",
			"gatsby_image_path":"..\/..\/images\/zombieland-double-tap.jpg",
			"slug":"zombieland-double-tap"
		},
		{
			"title":"Zathura: A Space Adventure",
			"gatsby_image_path":"..\/..\/images\/zathura-a-space-adventure.jpg",
			"slug":"zathura-a-space-adventure"
		},
		{
			"title":"Zack Snyder's Justice League",
			"gatsby_image_path":"..\/..\/images\/zack-snyder-s-justice-league.jpg",
			"slug":"zack-snyder-s-justice-league"
		},
		{
			"title":"Zack and Miri Make a Porno",
			"gatsby_image_path":"..\/..\/images\/zack-and-miri-make-a-porno.jpg",
			"slug":"zack-and-miri-make-a-porno"
		},
		{
			"title":"Yu-Gi-Oh!: The Dark Side of Dimensions",
			"gatsby_image_path":"..\/..\/images\/yu-gi-oh-the-dark-side-of-dimensions.jpg",
			"slug":"yu-gi-oh-the-dark-side-of-dimensions"
		},
		{
			"title":"Your Name",
			"gatsby_image_path":"..\/..\/images\/your-name.jpg",
			"slug":"your-name"
		},
		{
			"title":"Young Sister-in-law 3 - 2019",
			"gatsby_image_path":"..\/..\/images\/young-sister-in-law-3-2019.jpg",
			"slug":"young-sister-in-law-3-2019"
		},
		{
			"title":"Young and Wild",
			"gatsby_image_path":"..\/..\/images\/young-and-wild.jpg",
			"slug":"young-and-wild"
		},
		{
			"title":"Yes, No, or Maybe Half?",
			"gatsby_image_path":"..\/..\/images\/yes-no-or-maybe-half.jpg",
			"slug":"yes-no-or-maybe-half"
		},
		{
			"title":"Yes Man",
			"gatsby_image_path":"..\/..\/images\/yes-man.jpg",
			"slug":"yes-man"
		},
		{
			"title":"Yes Day",
			"gatsby_image_path":"..\/..\/images\/yes-day.jpg",
			"slug":"yes-day"
		},
		{
			"title":"Year One",
			"gatsby_image_path":"..\/..\/images\/year-one.jpg",
			"slug":"year-one"
		},
		{
			"title":"Yara",
			"gatsby_image_path":"..\/..\/images\/yara.jpg",
			"slug":"yara"
		}
	],
	"related_most_similar":[
		{
			"title":"The Kids Are Alright: Destination Asturias",
			"gatsby_image_path":"..\/..\/images\/the-kids-are-alright-destination-asturias.jpg",
			"slug":"the-kids-are-alright-destination-asturias"
		},
		{
			"title":"Klaus",
			"gatsby_image_path":"..\/..\/images\/klaus.jpg",
			"slug":"klaus"
		},
		{
			"title":"García y García",
			"gatsby_image_path":"..\/..\/images\/garcía-y-garcía.jpg",
			"slug":"garcía-y-garcía"
		},
		{
			"title":"Crazy About Her",
			"gatsby_image_path":"..\/..\/images\/crazy-about-her.jpg",
			"slug":"crazy-about-her"
		},
		{
			"title":"Three Steps Above Heaven",
			"gatsby_image_path":"..\/..\/images\/three-steps-above-heaven.jpg",
			"slug":"three-steps-above-heaven"
		},
		{
			"title":"The Invisible Guest",
			"gatsby_image_path":"..\/..\/images\/the-invisible-guest.jpg",
			"slug":"the-invisible-guest"
		},
		{
			"title":"The Cover",
			"gatsby_image_path":"..\/..\/images\/the-cover.jpg",
			"slug":"the-cover"
		},
		{
			"title":"Sounds Like Love",
			"gatsby_image_path":"..\/..\/images\/sounds-like-love.jpg",
			"slug":"sounds-like-love"
		},
		{
			"title":"Solo una vez",
			"gatsby_image_path":"..\/..\/images\/solo-una-vez.jpg",
			"slug":"solo-una-vez"
		},
		{
			"title":"Este amor es de otro planeta",
			"gatsby_image_path":"..\/..\/images\/este-amor-es-de-otro-planeta.jpg",
			"slug":"este-amor-es-de-otro-planeta"
		},
		{
			"title":"Underdogs",
			"gatsby_image_path":"..\/..\/images\/underdogs.jpg",
			"slug":"underdogs"
		},
		{
			"title":"Through My Window",
			"gatsby_image_path":"..\/..\/images\/through-my-window.jpg",
			"slug":"through-my-window"
		},
		{
			"title":"Tad, the Lost Explorer",
			"gatsby_image_path":"..\/..\/images\/tad-the-lost-explorer.jpg",
			"slug":"tad-the-lost-explorer"
		},
		{
			"title":"Sí, Mi Amor",
			"gatsby_image_path":"..\/..\/images\/sí-mi-amor.jpg",
			"slug":"sí-mi-amor"
		},
		{
			"title":"Sex with Love",
			"gatsby_image_path":"..\/..\/images\/sex-with-love.jpg",
			"slug":"sex-with-love"
		},
		{
			"title":"Sex, Party and Lies",
			"gatsby_image_path":"..\/..\/images\/sex-party-and-lies.jpg",
			"slug":"sex-party-and-lies"
		},
		{
			"title":"Sex and Lucía",
			"gatsby_image_path":"..\/..\/images\/sex-and-lucía.jpg",
			"slug":"sex-and-lucía"
		},
		{
			"title":"Seven Minutes",
			"gatsby_image_path":"..\/..\/images\/seven-minutes.jpg",
			"slug":"seven-minutes"
		},
		{
			"title":"Rosario Tijeras",
			"gatsby_image_path":"..\/..\/images\/rosario-tijeras.jpg",
			"slug":"rosario-tijeras"
		},
		{
			"title":"Possessed",
			"gatsby_image_path":"..\/..\/images\/possessed.jpg",
			"slug":"possessed"
		}
	],
	"related_by_poster":[
		{
			"title":"Mamma Mia!",
			"gatsby_image_path":"..\/..\/images\/mamma-mia.jpg",
			"slug":"mamma-mia"
		},
		{
			"title":"The Hangover Part II",
			"gatsby_image_path":"..\/..\/images\/the-hangover-part-ii.jpg",
			"slug":"the-hangover-part-ii"
		},
		{
			"title":"Knives Out",
			"gatsby_image_path":"..\/..\/images\/knives-out.jpg",
			"slug":"knives-out"
		},
		{
			"title":"Forgotten We’ll Be",
			"gatsby_image_path":"..\/..\/images\/forgotten-we’ll-be.jpg",
			"slug":"forgotten-we’ll-be"
		},
		{
			"title":"Deported",
			"gatsby_image_path":"..\/..\/images\/deported.jpg",
			"slug":"deported"
		},
		{
			"title":"Love Wedding Repeat",
			"gatsby_image_path":"..\/..\/images\/love-wedding-repeat.jpg",
			"slug":"love-wedding-repeat"
		},
		{
			"title":"The Lost Prince",
			"gatsby_image_path":"..\/..\/images\/the-lost-prince.jpg",
			"slug":"the-lost-prince"
		},
		{
			"title":"The Help",
			"gatsby_image_path":"..\/..\/images\/the-help.jpg",
			"slug":"the-help"
		},
		{
			"title":"Confessions of an Invisible Girl",
			"gatsby_image_path":"..\/..\/images\/confessions-of-an-invisible-girl.jpg",
			"slug":"confessions-of-an-invisible-girl"
		},
		{
			"title":"American Pie Presents: Band Camp",
			"gatsby_image_path":"..\/..\/images\/american-pie-presents-band-camp.jpg",
			"slug":"american-pie-presents-band-camp"
		},
		{
			"title":"Harry Potter and the Goblet of Fire",
			"gatsby_image_path":"..\/..\/images\/harry-potter-and-the-goblet-of-fire.jpg",
			"slug":"harry-potter-and-the-goblet-of-fire"
		},
		{
			"title":"Tom & Jerry",
			"gatsby_image_path":"..\/..\/images\/tom-jerry.jpg",
			"slug":"tom-jerry"
		},
		{
			"title":"Nanny McPhee",
			"gatsby_image_path":"..\/..\/images\/nanny-mcphee.jpg",
			"slug":"nanny-mcphee"
		},
		{
			"title":"Scooby-Doo 2: Monsters Unleashed",
			"gatsby_image_path":"..\/..\/images\/scooby-doo-2-monsters-unleashed.jpg",
			"slug":"scooby-doo-2-monsters-unleashed"
		},
		{
			"title":"The Monuments Men",
			"gatsby_image_path":"..\/..\/images\/the-monuments-men.jpg",
			"slug":"the-monuments-men"
		},
		{
			"title":"Prey",
			"gatsby_image_path":"..\/..\/images\/prey.jpg",
			"slug":"prey"
		},
		{
			"title":"Carriers",
			"gatsby_image_path":"..\/..\/images\/carriers.jpg",
			"slug":"carriers"
		},
		{
			"title":"Midway",
			"gatsby_image_path":"..\/..\/images\/midway.jpg",
			"slug":"midway"
		},
		{
			"title":"Gully",
			"gatsby_image_path":"..\/..\/images\/gully.jpg",
			"slug":"gully"
		},
		{
			"title":"Corpus Christi",
			"gatsby_image_path":"..\/..\/images\/corpus-christi.jpg",
			"slug":"corpus-christi"
		}
	],
	"related_by_overview":[
		{
			"title":"Evil Woman",
			"gatsby_image_path":"..\/..\/images\/evil-woman.jpg",
			"slug":"evil-woman"
		},
		{
			"title":"Crazy About Work",
			"gatsby_image_path":"..\/..\/images\/crazy-about-work.jpg",
			"slug":"crazy-about-work"
		},
		{
			"title":"Rosario Tijeras",
			"gatsby_image_path":"..\/..\/images\/rosario-tijeras.jpg",
			"slug":"rosario-tijeras"
		},
		{
			"title":"The Kids Are Alright: Destination Asturias",
			"gatsby_image_path":"..\/..\/images\/the-kids-are-alright-destination-asturias.jpg",
			"slug":"the-kids-are-alright-destination-asturias"
		},
		{
			"title":"Cindy La Regia",
			"gatsby_image_path":"..\/..\/images\/cindy-la-regia.jpg",
			"slug":"cindy-la-regia"
		},
		{
			"title":"The Intruder",
			"gatsby_image_path":"..\/..\/images\/the-intruder.jpg",
			"slug":"the-intruder"
		},
		{
			"title":"Tarumama",
			"gatsby_image_path":"..\/..\/images\/tarumama.jpg",
			"slug":"tarumama"
		},
		{
			"title":"War of Likes",
			"gatsby_image_path":"..\/..\/images\/war-of-likes.jpg",
			"slug":"war-of-likes"
		},
		{
			"title":"On a Magical Night",
			"gatsby_image_path":"..\/..\/images\/on-a-magical-night.jpg",
			"slug":"on-a-magical-night"
		},
		{
			"title":"BIA: An Upside Down World",
			"gatsby_image_path":"..\/..\/images\/bia-an-upside-down-world.jpg",
			"slug":"bia-an-upside-down-world"
		},
		{
			"title":"Barbie and the Diamond Castle",
			"gatsby_image_path":"..\/..\/images\/barbie-and-the-diamond-castle.jpg",
			"slug":"barbie-and-the-diamond-castle"
		},
		{
			"title":"There's Something About Mario",
			"gatsby_image_path":"..\/..\/images\/there-s-something-about-mario.jpg",
			"slug":"there-s-something-about-mario"
		},
		{
			"title":"Underdogs",
			"gatsby_image_path":"..\/..\/images\/underdogs.jpg",
			"slug":"underdogs"
		},
		{
			"title":"Ni tuyo, Ni mía",
			"gatsby_image_path":"..\/..\/images\/ni-tuyo-ni-mía.jpg",
			"slug":"ni-tuyo-ni-mía"
		},
		{
			"title":"Toxic",
			"gatsby_image_path":"..\/..\/images\/toxic.jpg",
			"slug":"toxic"
		},
		{
			"title":"Girl in the Basement",
			"gatsby_image_path":"..\/..\/images\/girl-in-the-basement.jpg",
			"slug":"girl-in-the-basement"
		},
		{
			"title":"Rich in Love",
			"gatsby_image_path":"..\/..\/images\/rich-in-love.jpg",
			"slug":"rich-in-love"
		},
		{
			"title":"Beverly Hills Chihuahua 3: Viva la Fiesta!",
			"gatsby_image_path":"..\/..\/images\/beverly-hills-chihuahua-3-viva-la-fiesta.jpg",
			"slug":"beverly-hills-chihuahua-3-viva-la-fiesta"
		},
		{
			"title":"The Invisible Man",
			"gatsby_image_path":"..\/..\/images\/the-invisible-man.jpg",
			"slug":"the-invisible-man"
		},
		{
			"title":"Isi & Ossi",
			"gatsby_image_path":"..\/..\/images\/isi-ossi.jpg",
			"slug":"isi-ossi"
		}
	],
	"tmdb_id":623926,
	"keywords":[],
	"tmdb_popularity":10
}